[
    {
        "id": 0,
        "name": "Arsenal Home Shirt",
        "desc": "Arsenal Home Shirt 2020/21",
        "price": 90,
        "front": "https://github.com/Souto751/project-imgs/blob/main/shirts/img/England/1/arsenal-home.png?raw=true",
        "back": "https://github.com/Souto751/project-imgs/blob/main/shirts/img/England/1/arsenal-home-back.png?raw=true",
        "team": "Arsenal",
        "league": "Premier League",
        "company": "Adidas",
        "colors": ["white", "red"]
    },
    {
        "id": 1,
        "name": "Arsenal Away Shirt",
        "desc": "Arsenal Away Shirt 2020/21",
        "price": 90,
        "front": "https://github.com/Souto751/project-imgs/blob/main/shirts/img/England/1/arsenal-away.png?raw=true",
        "back": "https://github.com/Souto751/project-imgs/blob/main/shirts/img/England/1/arsenal-away-back.png?raw=true",
        "team": "Arsenal",
        "league": "Premier League",
        "company": "Adidas",
        "colors": ["white"]
    },
    {
        "id": 2,
        "name": "Arsenal Third Shirt",
        "desc": "Arsenal Third Shirt 2020/21",
        "price": 90,
        "front": "https://github.com/Souto751/project-imgs/blob/main/shirts/img/England/1/arsenal-third.png?raw=true",
        "back": "https://github.com/Souto751/project-imgs/blob/main/shirts/img/England/1/arsenal-third-back.png?raw=true",
        "team": "Arsenal",
        "league": "Premier League",
        "company": "Adidas",
        "colors": ["blue"]
    },
    {
        "id": 3,
        "name": "Arsenal Goalkeeper Shirt",
        "desc": "Arsenal Goalkeeper Shirt 2020/21",
        "price": 90,
        "front": "https://github.com/Souto751/project-imgs/blob/main/shirts/img/England/1/arsenal-goalkeeper.png?raw=true",
        "back": "https://github.com/Souto751/project-imgs/blob/main/shirts/img/England/1/arsenal-goalkeeper-back.png?raw=true",
        "team": "Arsenal",
        "league": "Premier League",
        "company": "Adidas",
        "colors": ["black"]
    },
    {
        "id": 4,
        "name": "Aston Villa Home Shirt",
        "desc": "Aston Villa Home 2020/21",
        "price": 85,
        "front": "https://github.com/Souto751/project-imgs/blob/main/shirts/img/England/1/aston-villa-home.png?raw=true",
        "back": "https://github.com/Souto751/project-imgs/blob/main/shirts/img/England/1/aston-villa-home-back.png?raw=true",
        "team": "Aston Villa",
        "league": "Premier League",
        "company": "Kappa",
        "colors": ["red", "light blue"]
    },
    {
        "id": 5,
        "name": "Aston Villa Away Shirt",
        "desc": "Aston Villa Away Shirt 2020/21",
        "price": 85,
        "front": "https://github.com/Souto751/project-imgs/blob/main/shirts/img/England/1/aston-villa-away.png?raw=true",
        "back": "https://github.com/Souto751/project-imgs/blob/main/shirts/img/England/1/aston-villa-away-back.png?raw=true",
        "team": "Aston Villa",
        "league": "Premier League",
        "company": "Kappa",
        "colors": ["black"]
    },
    {
        "id": 6,
        "name": "Aston Villa Third Shirt",
        "desc": "Aston Villa Third Shirt 2020/21",
        "price": 85,
        "front": "https://github.com/Souto751/project-imgs/blob/main/shirts/img/England/1/aston-villa-third.png?raw=true",
        "back": "https://github.com/Souto751/project-imgs/blob/main/shirts/img/England/1/aston-villa-third-back.png?raw=true",
        "team": "Aston Villa",
        "league": "Premier League",
        "company": "Kappa",
        "colors": ["white", "gray"]
    },
    {
        "id": 7,
        "name": "Aston Villa Goalkeeper Home Shirt",
        "desc": "Aston Villa Goalkeeper Home Shirt 2020/21",
        "price": 85,
        "front": "https://github.com/Souto751/project-imgs/blob/main/shirts/img/England/1/aston-villa-goalkeeper.png?raw=true",
        "back": "https://github.com/Souto751/project-imgs/blob/main/shirts/img/England/1/aston-villa-goalkeeper-back.png?raw=true",
        "team": "Aston Villa",
        "league": "Premier League",
        "company": "Kappa",
        "colors": ["green"]
    },
    {
        "id": 8,
        "name": "Aston Villa Goalkeeper Away Shirt",
        "desc": "Aston Villa Goalkeeper Away Shirt 2020/21",
        "price": 85,
        "front": "https://github.com/Souto751/project-imgs/blob/main/shirts/img/England/1/aston-villa-goalkeeper-away.png?raw=true",
        "back": "https://github.com/Souto751/project-imgs/blob/main/shirts/img/England/1/aston-villa-goalkeeper-away-back.png?raw=true",
        "team": "Aston Villa",
        "league": "Premier League",
        "company": "Kappa",
        "colors": ["orange"]
    },
    {
        "id": 9,
        "name": "Aston Villa Goalkeeper Third Shirt",
        "desc": "Aston Villa Goalkeeper Third Shirt 2020/21",
        "price": 85,
        "front": "https://github.com/Souto751/project-imgs/blob/main/shirts/img/England/1/aston-villa-goalkeeper-third.png?raw=true",
        "back": "https://github.com/Souto751/project-imgs/blob/main/shirts/img/England/1/aston-villa-goalkeeper-third-back.png?raw=true",
        "team": "Aston Villa",
        "league": "Premier League",
        "company": "Kappa",
        "colors": ["blue"]
    },
    {
        "id": 10,
        "name": "Brighton Home Shirt",
        "desc": "Brighton Home Shirt 2020/21",
        "price": 85,
        "front": "https://github.com/Souto751/project-imgs/blob/main/shirts/img/England/1/brighton-home.png?raw=true",
        "back": "https://github.com/Souto751/project-imgs/blob/main/shirts/img/England/1/brighton-home-back.png?raw=true",
        "team": "Brighton",
        "league": "Premier League",
        "company": "Nike",
        "colors": ["blue"]
    },
    {
        "id": 11,
        "name": "Brighton Away Shirt",
        "desc": "Brighton Away Shirt 2020/21",
        "price": 85,
        "front": "https://github.com/Souto751/project-imgs/blob/main/shirts/img/England/1/brighton-away.png?raw=true",
        "back": "",
        "team": "Brighton",
        "league": "Premier League",
        "company": "Nike",
        "colors": ["yellow"]
    },
    {
        "id": 12,
        "name": "Brighton Third Shirt",
        "desc": "Brighton Third Shirt 2020/21",
        "price": 85,
        "front": "https://github.com/Souto751/project-imgs/blob/main/shirts/img/England/1/brighton-third.png?raw=true",
        "back": "https://github.com/Souto751/project-imgs/blob/main/shirts/img/England/1/brighton-third-back.png?raw=true",
        "team": "Brighton",
        "league": "Premier League",
        "company": "Nike",
        "colors": ["black", "gray"]
    },
    {
        "id": 13,
        "name": "Brighton Goalkeeper Green Shirt",
        "desc": "Brighton Goalkeeper Green Shirt 2020/21",
        "price": 85,
        "front": "https://github.com/Souto751/project-imgs/blob/main/shirts/img/England/1/brighton-goalkeeper-green.png?raw=true",
        "back": "",
        "team": "Brighton",
        "league": "Premier League",
        "company": "Nike",
        "colors": ["green"]
    },
    {
        "id": 14,
        "name": "Brighton Goalkeeper Orange Shirt",
        "desc": "Brighton Goalkeeper Orange Shirt 2020/21",
        "price": 85,
        "front": "https://github.com/Souto751/project-imgs/blob/main/shirts/img/England/1/brighton-goalkeeper-orange.png?raw=true",
        "back": "",
        "team": "Brighton",
        "league": "Premier League",
        "company": "Nike",
        "colors": ["orange"]
    },
    {
        "id": 2,
        "name": "Arsenal Third Shirt",
        "desc": "Arsenal Third Shirt 2020/21",
        "price": 90,
        "front": "https://github.com/Souto751/project-imgs/blob/main/shirts/img/England/1/arsenal-third.png?raw=true",
        "back": "https://github.com/Souto751/project-imgs/blob/main/shirts/img/England/1/arsenal-third-back.png?raw=true",
        "team": "Arsenal",
        "league": "Premier League",
        "colors": ["white", "red"]
    },
    {
        "id": 2,
        "name": "Arsenal Third Shirt",
        "desc": "Arsenal Third Shirt 2020/21",
        "price": 90,
        "front": "https://github.com/Souto751/project-imgs/blob/main/shirts/img/England/1/arsenal-third.png?raw=true",
        "back": "https://github.com/Souto751/project-imgs/blob/main/shirts/img/England/1/arsenal-third-back.png?raw=true",
        "team": "Arsenal",
        "league": "Premier League",
        "colors": ["white", "red"]
    },
    {
        "id": 2,
        "name": "Arsenal Third Shirt",
        "desc": "Arsenal Third Shirt 2020/21",
        "price": 90,
        "front": "https://github.com/Souto751/project-imgs/blob/main/shirts/img/England/1/arsenal-third.png?raw=true",
        "back": "https://github.com/Souto751/project-imgs/blob/main/shirts/img/England/1/arsenal-third-back.png?raw=true",
        "team": "Arsenal",
        "league": "Premier League",
        "colors": ["white", "red"]
    },
    {
        "id": 2,
        "name": "Arsenal Third Shirt",
        "desc": "Arsenal Third Shirt 2020/21",
        "price": 90,
        "front": "https://github.com/Souto751/project-imgs/blob/main/shirts/img/England/1/arsenal-third.png?raw=true",
        "back": "https://github.com/Souto751/project-imgs/blob/main/shirts/img/England/1/arsenal-third-back.png?raw=true",
        "team": "Arsenal",
        "league": "Premier League",
        "colors": ["white", "red"]
    },
    {
        "id": 2,
        "name": "Arsenal Third Shirt",
        "desc": "Arsenal Third Shirt 2020/21",
        "price": 90,
        "front": "https://github.com/Souto751/project-imgs/blob/main/shirts/img/England/1/arsenal-third.png?raw=true",
        "back": "https://github.com/Souto751/project-imgs/blob/main/shirts/img/England/1/arsenal-third-back.png?raw=true",
        "team": "Arsenal",
        "league": "Premier League",
        "colors": ["white", "red"]
    },
    {
        "id": 2,
        "name": "Arsenal Third Shirt",
        "desc": "Arsenal Third Shirt 2020/21",
        "price": 90,
        "front": "https://github.com/Souto751/project-imgs/blob/main/shirts/img/England/1/arsenal-third.png?raw=true",
        "back": "https://github.com/Souto751/project-imgs/blob/main/shirts/img/England/1/arsenal-third-back.png?raw=true",
        "team": "Arsenal",
        "league": "Premier League",
        "colors": ["white", "red"]
    },
    {
        "id": 2,
        "name": "Arsenal Third Shirt",
        "desc": "Arsenal Third Shirt 2020/21",
        "price": 90,
        "front": "https://github.com/Souto751/project-imgs/blob/main/shirts/img/England/1/arsenal-third.png?raw=true",
        "back": "https://github.com/Souto751/project-imgs/blob/main/shirts/img/England/1/arsenal-third-back.png?raw=true",
        "team": "Arsenal",
        "league": "Premier League",
        "colors": ["white", "red"]
    },
    {
        "id": 2,
        "name": "Arsenal Third Shirt",
        "desc": "Arsenal Third Shirt 2020/21",
        "price": 90,
        "front": "https://github.com/Souto751/project-imgs/blob/main/shirts/img/England/1/arsenal-third.png?raw=true",
        "back": "https://github.com/Souto751/project-imgs/blob/main/shirts/img/England/1/arsenal-third-back.png?raw=true",
        "team": "Arsenal",
        "league": "Premier League",
        "colors": ["white", "red"]
    },
    {
        "id": 2,
        "name": "Arsenal Third Shirt",
        "desc": "Arsenal Third Shirt 2020/21",
        "price": 90,
        "front": "https://github.com/Souto751/project-imgs/blob/main/shirts/img/England/1/arsenal-third.png?raw=true",
        "back": "https://github.com/Souto751/project-imgs/blob/main/shirts/img/England/1/arsenal-third-back.png?raw=true",
        "team": "Arsenal",
        "league": "Premier League",
        "colors": ["white", "red"]
    },
    {
        "id": 2,
        "name": "Arsenal Third Shirt",
        "desc": "Arsenal Third Shirt 2020/21",
        "price": 90,
        "front": "https://github.com/Souto751/project-imgs/blob/main/shirts/img/England/1/arsenal-third.png?raw=true",
        "back": "https://github.com/Souto751/project-imgs/blob/main/shirts/img/England/1/arsenal-third-back.png?raw=true",
        "team": "Arsenal",
        "league": "Premier League",
        "colors": ["white", "red"]
    },
    {
        "id": 2,
        "name": "Arsenal Third Shirt",
        "desc": "Arsenal Third Shirt 2020/21",
        "price": 90,
        "front": "https://github.com/Souto751/project-imgs/blob/main/shirts/img/England/1/arsenal-third.png?raw=true",
        "back": "https://github.com/Souto751/project-imgs/blob/main/shirts/img/England/1/arsenal-third-back.png?raw=true",
        "team": "Arsenal",
        "league": "Premier League",
        "colors": ["white", "red"]
    },
    {
        "id": 2,
        "name": "Arsenal Third Shirt",
        "desc": "Arsenal Third Shirt 2020/21",
        "price": 90,
        "front": "https://github.com/Souto751/project-imgs/blob/main/shirts/img/England/1/arsenal-third.png?raw=true",
        "back": "https://github.com/Souto751/project-imgs/blob/main/shirts/img/England/1/arsenal-third-back.png?raw=true",
        "team": "Arsenal",
        "league": "Premier League",
        "colors": ["white", "red"]
    },
    {
        "id": 2,
        "name": "Arsenal Third Shirt",
        "desc": "Arsenal Third Shirt 2020/21",
        "price": 90,
        "front": "https://github.com/Souto751/project-imgs/blob/main/shirts/img/England/1/arsenal-third.png?raw=true",
        "back": "https://github.com/Souto751/project-imgs/blob/main/shirts/img/England/1/arsenal-third-back.png?raw=true",
        "team": "Arsenal",
        "league": "Premier League",
        "colors": ["white", "red"]
    },
    {
        "id": 2,
        "name": "Arsenal Third Shirt",
        "desc": "Arsenal Third Shirt 2020/21",
        "price": 90,
        "front": "https://github.com/Souto751/project-imgs/blob/main/shirts/img/England/1/arsenal-third.png?raw=true",
        "back": "https://github.com/Souto751/project-imgs/blob/main/shirts/img/England/1/arsenal-third-back.png?raw=true",
        "team": "Arsenal",
        "league": "Premier League",
        "colors": ["white", "red"]
    },
    {
        "id": 2,
        "name": "Arsenal Third Shirt",
        "desc": "Arsenal Third Shirt 2020/21",
        "price": 90,
        "front": "https://github.com/Souto751/project-imgs/blob/main/shirts/img/England/1/arsenal-third.png?raw=true",
        "back": "https://github.com/Souto751/project-imgs/blob/main/shirts/img/England/1/arsenal-third-back.png?raw=true",
        "team": "Arsenal",
        "league": "Premier League",
        "colors": ["white", "red"]
    },
    {
        "id": 2,
        "name": "Arsenal Third Shirt",
        "desc": "Arsenal Third Shirt 2020/21",
        "price": 90,
        "front": "https://github.com/Souto751/project-imgs/blob/main/shirts/img/England/1/arsenal-third.png?raw=true",
        "back": "https://github.com/Souto751/project-imgs/blob/main/shirts/img/England/1/arsenal-third-back.png?raw=true",
        "team": "Arsenal",
        "league": "Premier League",
        "colors": ["white", "red"]
    },
    {
        "id": 2,
        "name": "Arsenal Third Shirt",
        "desc": "Arsenal Third Shirt 2020/21",
        "price": 90,
        "front": "https://github.com/Souto751/project-imgs/blob/main/shirts/img/England/1/arsenal-third.png?raw=true",
        "back": "https://github.com/Souto751/project-imgs/blob/main/shirts/img/England/1/arsenal-third-back.png?raw=true",
        "team": "Arsenal",
        "league": "Premier League",
        "colors": ["white", "red"]
    },
    {
        "id": 2,
        "name": "Arsenal Third Shirt",
        "desc": "Arsenal Third Shirt 2020/21",
        "price": 90,
        "front": "https://github.com/Souto751/project-imgs/blob/main/shirts/img/England/1/arsenal-third.png?raw=true",
        "back": "https://github.com/Souto751/project-imgs/blob/main/shirts/img/England/1/arsenal-third-back.png?raw=true",
        "team": "Arsenal",
        "league": "Premier League",
        "colors": ["white", "red"]
    },
    {
        "id": 2,
        "name": "Arsenal Third Shirt",
        "desc": "Arsenal Third Shirt 2020/21",
        "price": 90,
        "front": "https://github.com/Souto751/project-imgs/blob/main/shirts/img/England/1/arsenal-third.png?raw=true",
        "back": "https://github.com/Souto751/project-imgs/blob/main/shirts/img/England/1/arsenal-third-back.png?raw=true",
        "team": "Arsenal",
        "league": "Premier League",
        "colors": ["white", "red"]
    },
    {
        "id": 2,
        "name": "Arsenal Third Shirt",
        "desc": "Arsenal Third Shirt 2020/21",
        "price": 90,
        "front": "https://github.com/Souto751/project-imgs/blob/main/shirts/img/England/1/arsenal-third.png?raw=true",
        "back": "https://github.com/Souto751/project-imgs/blob/main/shirts/img/England/1/arsenal-third-back.png?raw=true",
        "team": "Arsenal",
        "league": "Premier League",
        "colors": ["white", "red"]
    },
    {
        "id": 2,
        "name": "Arsenal Third Shirt",
        "desc": "Arsenal Third Shirt 2020/21",
        "price": 90,
        "front": "https://github.com/Souto751/project-imgs/blob/main/shirts/img/England/1/arsenal-third.png?raw=true",
        "back": "https://github.com/Souto751/project-imgs/blob/main/shirts/img/England/1/arsenal-third-back.png?raw=true",
        "team": "Arsenal",
        "league": "Premier League",
        "colors": ["white", "red"]
    },
    {
        "id": 2,
        "name": "Arsenal Third Shirt",
        "desc": "Arsenal Third Shirt 2020/21",
        "price": 90,
        "front": "https://github.com/Souto751/project-imgs/blob/main/shirts/img/England/1/arsenal-third.png?raw=true",
        "back": "https://github.com/Souto751/project-imgs/blob/main/shirts/img/England/1/arsenal-third-back.png?raw=true",
        "team": "Arsenal",
        "league": "Premier League",
        "colors": ["white", "red"]
    },
    {
        "id": 2,
        "name": "Arsenal Third Shirt",
        "desc": "Arsenal Third Shirt 2020/21",
        "price": 90,
        "front": "https://github.com/Souto751/project-imgs/blob/main/shirts/img/England/1/arsenal-third.png?raw=true",
        "back": "https://github.com/Souto751/project-imgs/blob/main/shirts/img/England/1/arsenal-third-back.png?raw=true",
        "team": "Arsenal",
        "league": "Premier League",
        "colors": ["white", "red"]
    },
    {
        "id": 2,
        "name": "Arsenal Third Shirt",
        "desc": "Arsenal Third Shirt 2020/21",
        "price": 90,
        "front": "https://github.com/Souto751/project-imgs/blob/main/shirts/img/England/1/arsenal-third.png?raw=true",
        "back": "https://github.com/Souto751/project-imgs/blob/main/shirts/img/England/1/arsenal-third-back.png?raw=true",
        "team": "Arsenal",
        "league": "Premier League",
        "colors": ["white", "red"]
    },
    {
        "id": 2,
        "name": "Arsenal Third Shirt",
        "desc": "Arsenal Third Shirt 2020/21",
        "price": 90,
        "front": "https://github.com/Souto751/project-imgs/blob/main/shirts/img/England/1/arsenal-third.png?raw=true",
        "back": "https://github.com/Souto751/project-imgs/blob/main/shirts/img/England/1/arsenal-third-back.png?raw=true",
        "team": "Arsenal",
        "league": "Premier League",
        "colors": ["white", "red"]
    },
    {
        "id": 2,
        "name": "Arsenal Third Shirt",
        "desc": "Arsenal Third Shirt 2020/21",
        "price": 90,
        "front": "https://github.com/Souto751/project-imgs/blob/main/shirts/img/England/1/arsenal-third.png?raw=true",
        "back": "https://github.com/Souto751/project-imgs/blob/main/shirts/img/England/1/arsenal-third-back.png?raw=true",
        "team": "Arsenal",
        "league": "Premier League",
        "colors": ["white", "red"]
    },
    {
        "id": 2,
        "name": "Arsenal Third Shirt",
        "desc": "Arsenal Third Shirt 2020/21",
        "price": 90,
        "front": "https://github.com/Souto751/project-imgs/blob/main/shirts/img/England/1/arsenal-third.png?raw=true",
        "back": "https://github.com/Souto751/project-imgs/blob/main/shirts/img/England/1/arsenal-third-back.png?raw=true",
        "team": "Arsenal",
        "league": "Premier League",
        "colors": ["white", "red"]
    },
    {
        "id": 2,
        "name": "Arsenal Third Shirt",
        "desc": "Arsenal Third Shirt 2020/21",
        "price": 90,
        "front": "https://github.com/Souto751/project-imgs/blob/main/shirts/img/England/1/arsenal-third.png?raw=true",
        "back": "https://github.com/Souto751/project-imgs/blob/main/shirts/img/England/1/arsenal-third-back.png?raw=true",
        "team": "Arsenal",
        "league": "Premier League",
        "colors": ["white", "red"]
    },
    {
        "id": 2,
        "name": "Arsenal Third Shirt",
        "desc": "Arsenal Third Shirt 2020/21",
        "price": 90,
        "front": "https://github.com/Souto751/project-imgs/blob/main/shirts/img/England/1/arsenal-third.png?raw=true",
        "back": "https://github.com/Souto751/project-imgs/blob/main/shirts/img/England/1/arsenal-third-back.png?raw=true",
        "team": "Arsenal",
        "league": "Premier League",
        "colors": ["white", "red"]
    },
    {
        "id": 2,
        "name": "Arsenal Third Shirt",
        "desc": "Arsenal Third Shirt 2020/21",
        "price": 90,
        "front": "https://github.com/Souto751/project-imgs/blob/main/shirts/img/England/1/arsenal-third.png?raw=true",
        "back": "https://github.com/Souto751/project-imgs/blob/main/shirts/img/England/1/arsenal-third-back.png?raw=true",
        "team": "Arsenal",
        "league": "Premier League",
        "colors": ["white", "red"]
    },
    {
        "id": 2,
        "name": "Arsenal Third Shirt",
        "desc": "Arsenal Third Shirt 2020/21",
        "price": 90,
        "front": "https://github.com/Souto751/project-imgs/blob/main/shirts/img/England/1/arsenal-third.png?raw=true",
        "back": "https://github.com/Souto751/project-imgs/blob/main/shirts/img/England/1/arsenal-third-back.png?raw=true",
        "team": "Arsenal",
        "league": "Premier League",
        "colors": ["white", "red"]
    },
    {
        "id": 2,
        "name": "Arsenal Third Shirt",
        "desc": "Arsenal Third Shirt 2020/21",
        "price": 90,
        "front": "https://github.com/Souto751/project-imgs/blob/main/shirts/img/England/1/arsenal-third.png?raw=true",
        "back": "https://github.com/Souto751/project-imgs/blob/main/shirts/img/England/1/arsenal-third-back.png?raw=true",
        "team": "Arsenal",
        "league": "Premier League",
        "colors": ["white", "red"]
    },
    {
        "id": 2,
        "name": "Arsenal Third Shirt",
        "desc": "Arsenal Third Shirt 2020/21",
        "price": 90,
        "front": "https://github.com/Souto751/project-imgs/blob/main/shirts/img/England/1/arsenal-third.png?raw=true",
        "back": "https://github.com/Souto751/project-imgs/blob/main/shirts/img/England/1/arsenal-third-back.png?raw=true",
        "team": "Arsenal",
        "league": "Premier League",
        "colors": ["white", "red"]
    },
    {
        "id": 2,
        "name": "Arsenal Third Shirt",
        "desc": "Arsenal Third Shirt 2020/21",
        "price": 90,
        "front": "https://github.com/Souto751/project-imgs/blob/main/shirts/img/England/1/arsenal-third.png?raw=true",
        "back": "https://github.com/Souto751/project-imgs/blob/main/shirts/img/England/1/arsenal-third-back.png?raw=true",
        "team": "Arsenal",
        "league": "Premier League",
        "colors": ["white", "red"]
    },
    {
        "id": 2,
        "name": "Arsenal Third Shirt",
        "desc": "Arsenal Third Shirt 2020/21",
        "price": 90,
        "front": "https://github.com/Souto751/project-imgs/blob/main/shirts/img/England/1/arsenal-third.png?raw=true",
        "back": "https://github.com/Souto751/project-imgs/blob/main/shirts/img/England/1/arsenal-third-back.png?raw=true",
        "team": "Arsenal",
        "league": "Premier League",
        "colors": ["white", "red"]
    },
    {
        "id": 2,
        "name": "Arsenal Third Shirt",
        "desc": "Arsenal Third Shirt 2020/21",
        "price": 90,
        "front": "https://github.com/Souto751/project-imgs/blob/main/shirts/img/England/1/arsenal-third.png?raw=true",
        "back": "https://github.com/Souto751/project-imgs/blob/main/shirts/img/England/1/arsenal-third-back.png?raw=true",
        "team": "Arsenal",
        "league": "Premier League",
        "colors": ["white", "red"]
    },
    {
        "id": 2,
        "name": "Arsenal Third Shirt",
        "desc": "Arsenal Third Shirt 2020/21",
        "price": 90,
        "front": "https://github.com/Souto751/project-imgs/blob/main/shirts/img/England/1/arsenal-third.png?raw=true",
        "back": "https://github.com/Souto751/project-imgs/blob/main/shirts/img/England/1/arsenal-third-back.png?raw=true",
        "team": "Arsenal",
        "league": "Premier League",
        "colors": ["white", "red"]
    },
    {
        "id": 2,
        "name": "Arsenal Third Shirt",
        "desc": "Arsenal Third Shirt 2020/21",
        "price": 90,
        "front": "https://github.com/Souto751/project-imgs/blob/main/shirts/img/England/1/arsenal-third.png?raw=true",
        "back": "https://github.com/Souto751/project-imgs/blob/main/shirts/img/England/1/arsenal-third-back.png?raw=true",
        "team": "Arsenal",
        "league": "Premier League",
        "colors": ["white", "red"]
    },
    {
        "id": 2,
        "name": "Arsenal Third Shirt",
        "desc": "Arsenal Third Shirt 2020/21",
        "price": 90,
        "front": "https://github.com/Souto751/project-imgs/blob/main/shirts/img/England/1/arsenal-third.png?raw=true",
        "back": "https://github.com/Souto751/project-imgs/blob/main/shirts/img/England/1/arsenal-third-back.png?raw=true",
        "team": "Arsenal",
        "league": "Premier League",
        "colors": ["white", "red"]
    },
    {
        "id": 2,
        "name": "Arsenal Third Shirt",
        "desc": "Arsenal Third Shirt 2020/21",
        "price": 90,
        "front": "https://github.com/Souto751/project-imgs/blob/main/shirts/img/England/1/arsenal-third.png?raw=true",
        "back": "https://github.com/Souto751/project-imgs/blob/main/shirts/img/England/1/arsenal-third-back.png?raw=true",
        "team": "Arsenal",
        "league": "Premier League",
        "colors": ["white", "red"]
    },
    {
        "id": 2,
        "name": "Arsenal Third Shirt",
        "desc": "Arsenal Third Shirt 2020/21",
        "price": 90,
        "front": "https://github.com/Souto751/project-imgs/blob/main/shirts/img/England/1/arsenal-third.png?raw=true",
        "back": "https://github.com/Souto751/project-imgs/blob/main/shirts/img/England/1/arsenal-third-back.png?raw=true",
        "team": "Arsenal",
        "league": "Premier League",
        "colors": ["white", "red"]
    },
    {
        "id": 2,
        "name": "Arsenal Third Shirt",
        "desc": "Arsenal Third Shirt 2020/21",
        "price": 90,
        "front": "https://github.com/Souto751/project-imgs/blob/main/shirts/img/England/1/arsenal-third.png?raw=true",
        "back": "https://github.com/Souto751/project-imgs/blob/main/shirts/img/England/1/arsenal-third-back.png?raw=true",
        "team": "Arsenal",
        "league": "Premier League",
        "colors": ["white", "red"]
    },
    {
        "id": 2,
        "name": "Arsenal Third Shirt",
        "desc": "Arsenal Third Shirt 2020/21",
        "price": 90,
        "front": "https://github.com/Souto751/project-imgs/blob/main/shirts/img/England/1/arsenal-third.png?raw=true",
        "back": "https://github.com/Souto751/project-imgs/blob/main/shirts/img/England/1/arsenal-third-back.png?raw=true",
        "team": "Arsenal",
        "league": "Premier League",
        "colors": ["white", "red"]
    },
    {
        "id": 2,
        "name": "Arsenal Third Shirt",
        "desc": "Arsenal Third Shirt 2020/21",
        "price": 90,
        "front": "https://github.com/Souto751/project-imgs/blob/main/shirts/img/England/1/arsenal-third.png?raw=true",
        "back": "https://github.com/Souto751/project-imgs/blob/main/shirts/img/England/1/arsenal-third-back.png?raw=true",
        "team": "Arsenal",
        "league": "Premier League",
        "colors": ["white", "red"]
    },
    {
        "id": 2,
        "name": "Arsenal Third Shirt",
        "desc": "Arsenal Third Shirt 2020/21",
        "price": 90,
        "front": "https://github.com/Souto751/project-imgs/blob/main/shirts/img/England/1/arsenal-third.png?raw=true",
        "back": "https://github.com/Souto751/project-imgs/blob/main/shirts/img/England/1/arsenal-third-back.png?raw=true",
        "team": "Arsenal",
        "league": "Premier League",
        "colors": ["white", "red"]
    },
    {
        "id": 2,
        "name": "Arsenal Third Shirt",
        "desc": "Arsenal Third Shirt 2020/21",
        "price": 90,
        "front": "https://github.com/Souto751/project-imgs/blob/main/shirts/img/England/1/arsenal-third.png?raw=true",
        "back": "https://github.com/Souto751/project-imgs/blob/main/shirts/img/England/1/arsenal-third-back.png?raw=true",
        "team": "Arsenal",
        "league": "Premier League",
        "colors": ["white", "red"]
    },
    {
        "id": 2,
        "name": "Arsenal Third Shirt",
        "desc": "Arsenal Third Shirt 2020/21",
        "price": 90,
        "front": "https://github.com/Souto751/project-imgs/blob/main/shirts/img/England/1/arsenal-third.png?raw=true",
        "back": "https://github.com/Souto751/project-imgs/blob/main/shirts/img/England/1/arsenal-third-back.png?raw=true",
        "team": "Arsenal",
        "league": "Premier League",
        "colors": ["white", "red"]
    },
    {
        "id": 2,
        "name": "Arsenal Third Shirt",
        "desc": "Arsenal Third Shirt 2020/21",
        "price": 90,
        "front": "https://github.com/Souto751/project-imgs/blob/main/shirts/img/England/1/arsenal-third.png?raw=true",
        "back": "https://github.com/Souto751/project-imgs/blob/main/shirts/img/England/1/arsenal-third-back.png?raw=true",
        "team": "Arsenal",
        "league": "Premier League",
        "colors": ["white", "red"]
    },
    {
        "id": 2,
        "name": "Arsenal Third Shirt",
        "desc": "Arsenal Third Shirt 2020/21",
        "price": 90,
        "front": "https://github.com/Souto751/project-imgs/blob/main/shirts/img/England/1/arsenal-third.png?raw=true",
        "back": "https://github.com/Souto751/project-imgs/blob/main/shirts/img/England/1/arsenal-third-back.png?raw=true",
        "team": "Arsenal",
        "league": "Premier League",
        "colors": ["white", "red"]
    },
    {
        "id": 2,
        "name": "Arsenal Third Shirt",
        "desc": "Arsenal Third Shirt 2020/21",
        "price": 90,
        "front": "https://github.com/Souto751/project-imgs/blob/main/shirts/img/England/1/arsenal-third.png?raw=true",
        "back": "https://github.com/Souto751/project-imgs/blob/main/shirts/img/England/1/arsenal-third-back.png?raw=true",
        "team": "Arsenal",
        "league": "Premier League",
        "colors": ["white", "red"]
    },
    {
        "id": 2,
        "name": "Arsenal Third Shirt",
        "desc": "Arsenal Third Shirt 2020/21",
        "price": 90,
        "front": "https://github.com/Souto751/project-imgs/blob/main/shirts/img/England/1/arsenal-third.png?raw=true",
        "back": "https://github.com/Souto751/project-imgs/blob/main/shirts/img/England/1/arsenal-third-back.png?raw=true",
        "team": "Arsenal",
        "league": "Premier League",
        "colors": ["white", "red"]
    },
    {
        "id": 2,
        "name": "Arsenal Third Shirt",
        "desc": "Arsenal Third Shirt 2020/21",
        "price": 90,
        "front": "https://github.com/Souto751/project-imgs/blob/main/shirts/img/England/1/arsenal-third.png?raw=true",
        "back": "https://github.com/Souto751/project-imgs/blob/main/shirts/img/England/1/arsenal-third-back.png?raw=true",
        "team": "Arsenal",
        "league": "Premier League",
        "colors": ["white", "red"]
    },
    {
        "id": 2,
        "name": "Arsenal Third Shirt",
        "desc": "Arsenal Third Shirt 2020/21",
        "price": 90,
        "front": "https://github.com/Souto751/project-imgs/blob/main/shirts/img/England/1/arsenal-third.png?raw=true",
        "back": "https://github.com/Souto751/project-imgs/blob/main/shirts/img/England/1/arsenal-third-back.png?raw=true",
        "team": "Arsenal",
        "league": "Premier League",
        "colors": ["white", "red"]
    },
    {
        "id": 2,
        "name": "Arsenal Third Shirt",
        "desc": "Arsenal Third Shirt 2020/21",
        "price": 90,
        "front": "https://github.com/Souto751/project-imgs/blob/main/shirts/img/England/1/arsenal-third.png?raw=true",
        "back": "https://github.com/Souto751/project-imgs/blob/main/shirts/img/England/1/arsenal-third-back.png?raw=true",
        "team": "Arsenal",
        "league": "Premier League",
        "colors": ["white", "red"]
    },
    {
        "id": 2,
        "name": "Arsenal Third Shirt",
        "desc": "Arsenal Third Shirt 2020/21",
        "price": 90,
        "front": "https://github.com/Souto751/project-imgs/blob/main/shirts/img/England/1/arsenal-third.png?raw=true",
        "back": "https://github.com/Souto751/project-imgs/blob/main/shirts/img/England/1/arsenal-third-back.png?raw=true",
        "team": "Arsenal",
        "league": "Premier League",
        "colors": ["white", "red"]
    },
    {
        "id": 2,
        "name": "Arsenal Third Shirt",
        "desc": "Arsenal Third Shirt 2020/21",
        "price": 90,
        "front": "https://github.com/Souto751/project-imgs/blob/main/shirts/img/England/1/arsenal-third.png?raw=true",
        "back": "https://github.com/Souto751/project-imgs/blob/main/shirts/img/England/1/arsenal-third-back.png?raw=true",
        "team": "Arsenal",
        "league": "Premier League",
        "colors": ["white", "red"]
    },
    {
        "id": 2,
        "name": "Arsenal Third Shirt",
        "desc": "Arsenal Third Shirt 2020/21",
        "price": 90,
        "front": "https://github.com/Souto751/project-imgs/blob/main/shirts/img/England/1/arsenal-third.png?raw=true",
        "back": "https://github.com/Souto751/project-imgs/blob/main/shirts/img/England/1/arsenal-third-back.png?raw=true",
        "team": "Arsenal",
        "league": "Premier League",
        "colors": ["white", "red"]
    },
    {
        "id": 2,
        "name": "Arsenal Third Shirt",
        "desc": "Arsenal Third Shirt 2020/21",
        "price": 90,
        "front": "https://github.com/Souto751/project-imgs/blob/main/shirts/img/England/1/arsenal-third.png?raw=true",
        "back": "https://github.com/Souto751/project-imgs/blob/main/shirts/img/England/1/arsenal-third-back.png?raw=true",
        "team": "Arsenal",
        "league": "Premier League",
        "colors": ["white", "red"]
    },
    {
        "id": 2,
        "name": "Arsenal Third Shirt",
        "desc": "Arsenal Third Shirt 2020/21",
        "price": 90,
        "front": "https://github.com/Souto751/project-imgs/blob/main/shirts/img/England/1/arsenal-third.png?raw=true",
        "back": "https://github.com/Souto751/project-imgs/blob/main/shirts/img/England/1/arsenal-third-back.png?raw=true",
        "team": "Arsenal",
        "league": "Premier League",
        "colors": ["white", "red"]
    },
    {
        "id": 2,
        "name": "Arsenal Third Shirt",
        "desc": "Arsenal Third Shirt 2020/21",
        "price": 90,
        "front": "https://github.com/Souto751/project-imgs/blob/main/shirts/img/England/1/arsenal-third.png?raw=true",
        "back": "https://github.com/Souto751/project-imgs/blob/main/shirts/img/England/1/arsenal-third-back.png?raw=true",
        "team": "Arsenal",
        "league": "Premier League",
        "colors": ["white", "red"]
    },
    {
        "id": 2,
        "name": "Arsenal Third Shirt",
        "desc": "Arsenal Third Shirt 2020/21",
        "price": 90,
        "front": "https://github.com/Souto751/project-imgs/blob/main/shirts/img/England/1/arsenal-third.png?raw=true",
        "back": "https://github.com/Souto751/project-imgs/blob/main/shirts/img/England/1/arsenal-third-back.png?raw=true",
        "team": "Arsenal",
        "league": "Premier League",
        "colors": ["white", "red"]
    },
    {
        "id": 2,
        "name": "Arsenal Third Shirt",
        "desc": "Arsenal Third Shirt 2020/21",
        "price": 90,
        "front": "https://github.com/Souto751/project-imgs/blob/main/shirts/img/England/1/arsenal-third.png?raw=true",
        "back": "https://github.com/Souto751/project-imgs/blob/main/shirts/img/England/1/arsenal-third-back.png?raw=true",
        "team": "Arsenal",
        "league": "Premier League",
        "colors": ["white", "red"]
    },
    {
        "id": 2,
        "name": "Arsenal Third Shirt",
        "desc": "Arsenal Third Shirt 2020/21",
        "price": 90,
        "front": "https://github.com/Souto751/project-imgs/blob/main/shirts/img/England/1/arsenal-third.png?raw=true",
        "back": "https://github.com/Souto751/project-imgs/blob/main/shirts/img/England/1/arsenal-third-back.png?raw=true",
        "team": "Arsenal",
        "league": "Premier League",
        "colors": ["white", "red"]
    },
    {
        "id": 2,
        "name": "Arsenal Third Shirt",
        "desc": "Arsenal Third Shirt 2020/21",
        "price": 90,
        "front": "https://github.com/Souto751/project-imgs/blob/main/shirts/img/England/1/arsenal-third.png?raw=true",
        "back": "https://github.com/Souto751/project-imgs/blob/main/shirts/img/England/1/arsenal-third-back.png?raw=true",
        "team": "Arsenal",
        "league": "Premier League",
        "colors": ["white", "red"]
    },
    {
        "id": 2,
        "name": "Arsenal Third Shirt",
        "desc": "Arsenal Third Shirt 2020/21",
        "price": 90,
        "front": "https://github.com/Souto751/project-imgs/blob/main/shirts/img/England/1/arsenal-third.png?raw=true",
        "back": "https://github.com/Souto751/project-imgs/blob/main/shirts/img/England/1/arsenal-third-back.png?raw=true",
        "team": "Arsenal",
        "league": "Premier League",
        "colors": ["white", "red"]
    },
    {
        "id": 2,
        "name": "Arsenal Third Shirt",
        "desc": "Arsenal Third Shirt 2020/21",
        "price": 90,
        "front": "https://github.com/Souto751/project-imgs/blob/main/shirts/img/England/1/arsenal-third.png?raw=true",
        "back": "https://github.com/Souto751/project-imgs/blob/main/shirts/img/England/1/arsenal-third-back.png?raw=true",
        "team": "Arsenal",
        "league": "Premier League",
        "colors": ["white", "red"]
    },
    {
        "id": 2,
        "name": "Arsenal Third Shirt",
        "desc": "Arsenal Third Shirt 2020/21",
        "price": 90,
        "front": "https://github.com/Souto751/project-imgs/blob/main/shirts/img/England/1/arsenal-third.png?raw=true",
        "back": "https://github.com/Souto751/project-imgs/blob/main/shirts/img/England/1/arsenal-third-back.png?raw=true",
        "team": "Arsenal",
        "league": "Premier League",
        "colors": ["white", "red"]
    },
    {
        "id": 2,
        "name": "Arsenal Third Shirt",
        "desc": "Arsenal Third Shirt 2020/21",
        "price": 90,
        "front": "https://github.com/Souto751/project-imgs/blob/main/shirts/img/England/1/arsenal-third.png?raw=true",
        "back": "https://github.com/Souto751/project-imgs/blob/main/shirts/img/England/1/arsenal-third-back.png?raw=true",
        "team": "Arsenal",
        "league": "Premier League",
        "colors": ["white", "red"]
    },
    {
        "id": 2,
        "name": "Arsenal Third Shirt",
        "desc": "Arsenal Third Shirt 2020/21",
        "price": 90,
        "front": "https://github.com/Souto751/project-imgs/blob/main/shirts/img/England/1/arsenal-third.png?raw=true",
        "back": "https://github.com/Souto751/project-imgs/blob/main/shirts/img/England/1/arsenal-third-back.png?raw=true",
        "team": "Arsenal",
        "league": "Premier League",
        "colors": ["white", "red"]
    },
    {
        "id": 2,
        "name": "Arsenal Third Shirt",
        "desc": "Arsenal Third Shirt 2020/21",
        "price": 90,
        "front": "https://github.com/Souto751/project-imgs/blob/main/shirts/img/England/1/arsenal-third.png?raw=true",
        "back": "https://github.com/Souto751/project-imgs/blob/main/shirts/img/England/1/arsenal-third-back.png?raw=true",
        "team": "Arsenal",
        "league": "Premier League",
        "colors": ["white", "red"]
    },
    {
        "id": 2,
        "name": "Arsenal Third Shirt",
        "desc": "Arsenal Third Shirt 2020/21",
        "price": 90,
        "front": "https://github.com/Souto751/project-imgs/blob/main/shirts/img/England/1/arsenal-third.png?raw=true",
        "back": "https://github.com/Souto751/project-imgs/blob/main/shirts/img/England/1/arsenal-third-back.png?raw=true",
        "team": "Arsenal",
        "league": "Premier League",
        "colors": ["white", "red"]
    },
    {
        "id": 2,
        "name": "Arsenal Third Shirt",
        "desc": "Arsenal Third Shirt 2020/21",
        "price": 90,
        "front": "https://github.com/Souto751/project-imgs/blob/main/shirts/img/England/1/arsenal-third.png?raw=true",
        "back": "https://github.com/Souto751/project-imgs/blob/main/shirts/img/England/1/arsenal-third-back.png?raw=true",
        "team": "Arsenal",
        "league": "Premier League",
        "colors": ["white", "red"]
    },
    {
        "id": 2,
        "name": "Arsenal Third Shirt",
        "desc": "Arsenal Third Shirt 2020/21",
        "price": 90,
        "front": "https://github.com/Souto751/project-imgs/blob/main/shirts/img/England/1/arsenal-third.png?raw=true",
        "back": "https://github.com/Souto751/project-imgs/blob/main/shirts/img/England/1/arsenal-third-back.png?raw=true",
        "team": "Arsenal",
        "league": "Premier League",
        "colors": ["white", "red"]
    },
    {
        "id": 2,
        "name": "Arsenal Third Shirt",
        "desc": "Arsenal Third Shirt 2020/21",
        "price": 90,
        "front": "https://github.com/Souto751/project-imgs/blob/main/shirts/img/England/1/arsenal-third.png?raw=true",
        "back": "https://github.com/Souto751/project-imgs/blob/main/shirts/img/England/1/arsenal-third-back.png?raw=true",
        "team": "Arsenal",
        "league": "Premier League",
        "colors": ["white", "red"]
    },
    {
        "id": 2,
        "name": "Arsenal Third Shirt",
        "desc": "Arsenal Third Shirt 2020/21",
        "price": 90,
        "front": "https://github.com/Souto751/project-imgs/blob/main/shirts/img/England/1/arsenal-third.png?raw=true",
        "back": "https://github.com/Souto751/project-imgs/blob/main/shirts/img/England/1/arsenal-third-back.png?raw=true",
        "team": "Arsenal",
        "league": "Premier League",
        "colors": ["white", "red"]
    },
    {
        "id": 2,
        "name": "Arsenal Third Shirt",
        "desc": "Arsenal Third Shirt 2020/21",
        "price": 90,
        "front": "https://github.com/Souto751/project-imgs/blob/main/shirts/img/England/1/arsenal-third.png?raw=true",
        "back": "https://github.com/Souto751/project-imgs/blob/main/shirts/img/England/1/arsenal-third-back.png?raw=true",
        "team": "Arsenal",
        "league": "Premier League",
        "colors": ["white", "red"]
    },
    {
        "id": 2,
        "name": "Arsenal Third Shirt",
        "desc": "Arsenal Third Shirt 2020/21",
        "price": 90,
        "front": "https://github.com/Souto751/project-imgs/blob/main/shirts/img/England/1/arsenal-third.png?raw=true",
        "back": "https://github.com/Souto751/project-imgs/blob/main/shirts/img/England/1/arsenal-third-back.png?raw=true",
        "team": "Arsenal",
        "league": "Premier League",
        "colors": ["white", "red"]
    },
    {
        "id": 2,
        "name": "Arsenal Third Shirt",
        "desc": "Arsenal Third Shirt 2020/21",
        "price": 90,
        "front": "https://github.com/Souto751/project-imgs/blob/main/shirts/img/England/1/arsenal-third.png?raw=true",
        "back": "https://github.com/Souto751/project-imgs/blob/main/shirts/img/England/1/arsenal-third-back.png?raw=true",
        "team": "Arsenal",
        "league": "Premier League",
        "colors": ["white", "red"]
    },
    {
        "id": 2,
        "name": "Arsenal Third Shirt",
        "desc": "Arsenal Third Shirt 2020/21",
        "price": 90,
        "front": "https://github.com/Souto751/project-imgs/blob/main/shirts/img/England/1/arsenal-third.png?raw=true",
        "back": "https://github.com/Souto751/project-imgs/blob/main/shirts/img/England/1/arsenal-third-back.png?raw=true",
        "team": "Arsenal",
        "league": "Premier League",
        "colors": ["white", "red"]
    },
    {
        "id": 2,
        "name": "Arsenal Third Shirt",
        "desc": "Arsenal Third Shirt 2020/21",
        "price": 90,
        "front": "https://github.com/Souto751/project-imgs/blob/main/shirts/img/England/1/arsenal-third.png?raw=true",
        "back": "https://github.com/Souto751/project-imgs/blob/main/shirts/img/England/1/arsenal-third-back.png?raw=true",
        "team": "Arsenal",
        "league": "Premier League",
        "colors": ["white", "red"]
    },
    {
        "id": 2,
        "name": "Arsenal Third Shirt",
        "desc": "Arsenal Third Shirt 2020/21",
        "price": 90,
        "front": "https://github.com/Souto751/project-imgs/blob/main/shirts/img/England/1/arsenal-third.png?raw=true",
        "back": "https://github.com/Souto751/project-imgs/blob/main/shirts/img/England/1/arsenal-third-back.png?raw=true",
        "team": "Arsenal",
        "league": "Premier League",
        "colors": ["white", "red"]
    },
    {
        "id": 2,
        "name": "Arsenal Third Shirt",
        "desc": "Arsenal Third Shirt 2020/21",
        "price": 90,
        "front": "https://github.com/Souto751/project-imgs/blob/main/shirts/img/England/1/arsenal-third.png?raw=true",
        "back": "https://github.com/Souto751/project-imgs/blob/main/shirts/img/England/1/arsenal-third-back.png?raw=true",
        "team": "Arsenal",
        "league": "Premier League",
        "colors": ["white", "red"]
    },
    {
        "id": 2,
        "name": "Arsenal Third Shirt",
        "desc": "Arsenal Third Shirt 2020/21",
        "price": 90,
        "front": "https://github.com/Souto751/project-imgs/blob/main/shirts/img/England/1/arsenal-third.png?raw=true",
        "back": "https://github.com/Souto751/project-imgs/blob/main/shirts/img/England/1/arsenal-third-back.png?raw=true",
        "team": "Arsenal",
        "league": "Premier League",
        "colors": ["white", "red"]
    },
    {
        "id": 2,
        "name": "Arsenal Third Shirt",
        "desc": "Arsenal Third Shirt 2020/21",
        "price": 90,
        "front": "https://github.com/Souto751/project-imgs/blob/main/shirts/img/England/1/arsenal-third.png?raw=true",
        "back": "https://github.com/Souto751/project-imgs/blob/main/shirts/img/England/1/arsenal-third-back.png?raw=true",
        "team": "Arsenal",
        "league": "Premier League",
        "colors": ["white", "red"]
    },
    {
        "id": 2,
        "name": "Arsenal Third Shirt",
        "desc": "Arsenal Third Shirt 2020/21",
        "price": 90,
        "front": "https://github.com/Souto751/project-imgs/blob/main/shirts/img/England/1/arsenal-third.png?raw=true",
        "back": "https://github.com/Souto751/project-imgs/blob/main/shirts/img/England/1/arsenal-third-back.png?raw=true",
        "team": "Arsenal",
        "league": "Premier League",
        "colors": ["white", "red"]
    },
    {
        "id": 2,
        "name": "Arsenal Third Shirt",
        "desc": "Arsenal Third Shirt 2020/21",
        "price": 90,
        "front": "https://github.com/Souto751/project-imgs/blob/main/shirts/img/England/1/arsenal-third.png?raw=true",
        "back": "https://github.com/Souto751/project-imgs/blob/main/shirts/img/England/1/arsenal-third-back.png?raw=true",
        "team": "Arsenal",
        "league": "Premier League",
        "colors": ["white", "red"]
    }
]